{
  "$schema": "https://raw.githubusercontent.com/rroodll/QB-Estimate-Reporting/main/schema/resource_estimate_schema.json",
  "id": "FH 128x128 Square (U/J = 4.0)",
  "name": "Fermi-Hubbard",
  "category": "scientific",
  "size": "128 x 128",
  "task": "time_independent_dynamics",
  "implementation": "QET w/ Linear-T FH Encoding",
  "value": 50000000.0,
  "value_ci": [50e5, 50e7], 
  "value_per_t_gate": 8.26e-7,
  "circuit_repetitions_per_calculation": 100,
  "calculation_repetitions": 10,
  "total_circuit_repetitions": 1000,
  "runtime_requirement": 115200,  
    "logical-abstract": {
    "num_qubits": 32804,
    "t_count": 60549453290,
    "clifford_count": 310704519223
  }
}